mkdocs_bootstrap386/__init__.py
mkdocs_bootstrap386/base.html
mkdocs_bootstrap386/content.html
mkdocs_bootstrap386/main.html
mkdocs_bootstrap386/mkdocs_theme.yml
mkdocs_bootstrap386/nav.html
mkdocs_bootstrap386/search.html
mkdocs_bootstrap386/toc.html
mkdocs_bootstrap386/css/bootstrap-theme.min.css
mkdocs_bootstrap386/css/bootstrap.min.css
mkdocs_bootstrap386/css/font-awesome.min.css
mkdocs_bootstrap386/css/highlight.css
mkdocs_bootstrap386/css/fonts/Fixedsys500c.eot
mkdocs_bootstrap386/css/fonts/Fixedsys500c.svg
mkdocs_bootstrap386/css/fonts/Fixedsys500c.ttf
mkdocs_bootstrap386/css/fonts/Fixedsys500c.woff
mkdocs_bootstrap386/css/fonts/fonts/Fixedsys500c.eot
mkdocs_bootstrap386/css/fonts/fonts/Fixedsys500c.svg
mkdocs_bootstrap386/css/fonts/fonts/Fixedsys500c.ttf
mkdocs_bootstrap386/css/fonts/fonts/Fixedsys500c.woff
mkdocs_bootstrap386/fonts/fontawesome-webfont.eot
mkdocs_bootstrap386/fonts/fontawesome-webfont.svg
mkdocs_bootstrap386/fonts/fontawesome-webfont.ttf
mkdocs_bootstrap386/fonts/fontawesome-webfont.woff
mkdocs_bootstrap386/fonts/fontawesome-webfont.woff2
mkdocs_bootstrap386/fonts/glyphicons-halflings-regular.eot
mkdocs_bootstrap386/fonts/glyphicons-halflings-regular.svg
mkdocs_bootstrap386/fonts/glyphicons-halflings-regular.ttf
mkdocs_bootstrap386/fonts/glyphicons-halflings-regular.woff
mkdocs_bootstrap386/fonts/glyphicons-halflings-regular.woff2
mkdocs_bootstrap386/img/favicon.ico
mkdocs_bootstrap386/js/bootstrap.min.js
mkdocs_bootstrap386/js/jquery-1.10.2.min.js
mkdocs_bootstrap386-0.0.2.dist-info/LICENSE
mkdocs_bootstrap386-0.0.2.dist-info/METADATA
mkdocs_bootstrap386-0.0.2.dist-info/WHEEL
mkdocs_bootstrap386-0.0.2.dist-info/entry_points.txt
mkdocs_bootstrap386-0.0.2.dist-info/top_level.txt
mkdocs_bootstrap386-0.0.2.dist-info/RECORD
