Metadata-Version: 2.1
Name: mkdocs-bootstrap386
Version: 0.0.2
Summary: A vintage 1980s DOS inspired Twitter Bootstrap theme for MkDocs
Home-page: https://gitlab.com/lramage94/mkdocs-bootstrap386
Author: Lucas Ramage
Author-email: ramage.lucas@protonmail.com
License: BSD
Platform: UNKNOWN
